{
	"info": {
		"_postman_id": "dbff473d-0bf4-455c-94ce-f1a68021d729",
		"name": "Lumen Product Api",
		"schema": "https://schema.getpostman.com/json/collection/v2.1.0/collection.json",
		"_exporter_id": "3124823"
	},
	"item": [
		{
			"name": "Create Product",
			"request": {
				"method": "GET",
				"header": []
			},
			"response": []
		},
		{
			"name": "All Products",
			"request": {
				"method": "GET",
				"header": []
			},
			"response": []
		},
		{
			"name": "Single Product",
			"request": {
				"method": "GET",
				"header": []
			},
			"response": []
		},
		{
			"name": "Update Product",
			"request": {
				"method": "GET",
				"header": []
			},
			"response": []
		},
		{
			"name": "New Request",
			"request": {
				"method": "GET",
				"header": []
			},
			"response": []
		}
	]
}